blue_flie/README.py
blue_flie/__init__.py
blue_flie/__main__.py
blue_flie/config.env
blue_flie/env.py
blue_flie/fpv.py
blue_flie/host.py
blue_flie/logger.py
blue_flie/sample.env
blue_flie/urls.py
blue_flie/.abcli/abcli.sh
blue_flie/.abcli/actions.sh
blue_flie/.abcli/aka.sh
blue_flie/.abcli/alias.sh
blue_flie/.abcli/blue_flie.sh
blue_flie/.abcli/browse.sh
blue_flie/.abcli/gazebo.sh
blue_flie/.abcli/install.sh
blue_flie/.abcli/toolbelt.sh
blue_flie/.abcli/gazebo/browse.sh
blue_flie/.abcli/gazebo/ingest.sh
blue_flie/.abcli/gazebo/install.sh
blue_flie/.abcli/tests/README.sh
blue_flie/.abcli/tests/gazebo_browse.sh
blue_flie/.abcli/tests/gazebo_ingest.sh
blue_flie/.abcli/tests/gazebo_ingest_browse.sh
blue_flie/.abcli/tests/gazebo_ingest_list.sh
blue_flie/.abcli/tests/help.sh
blue_flie/.abcli/tests/version.sh
blue_flie/.abcli/toolbelt/install.sh
blue_flie/gazebo/__init__.py
blue_flie/gazebo/__main__.py
blue_flie/gazebo/functions.py
blue_flie/help/__init__.py
blue_flie/help/__main__.py
blue_flie/help/functions.py
blue_flie/help/gazebo.py
blue_flie/help/toolbelt.py
blue_flie-4.122.1.dist-info/LICENSE
blue_flie-4.122.1.dist-info/METADATA
blue_flie-4.122.1.dist-info/WHEEL
blue_flie-4.122.1.dist-info/top_level.txt
blue_flie-4.122.1.dist-info/RECORD
